MANIFEST.in
README.rst
bootstrap.py
setup.py
docs/CHANGES.rst
docs/INSTALL.rst
docs/LICENSE.GPL
docs/LICENSE.txt
src/collective/__init__.py
src/collective.js.leaflet.egg-info/PKG-INFO
src/collective.js.leaflet.egg-info/SOURCES.txt
src/collective.js.leaflet.egg-info/dependency_links.txt
src/collective.js.leaflet.egg-info/entry_points.txt
src/collective.js.leaflet.egg-info/namespace_packages.txt
src/collective.js.leaflet.egg-info/requires.txt
src/collective.js.leaflet.egg-info/top_level.txt
src/collective/js/__init__.py
src/collective/js/leaflet/__init__.py
src/collective/js/leaflet/app_config.py
src/collective/js/leaflet/configure.zcml
src/collective/js/leaflet/interfaces.py
src/collective/js/leaflet/profiles.zcml
src/collective/js/leaflet/rebuild_i18n.sh
src/collective/js/leaflet/testing.py
src/collective/js/leaflet/upgrades.py
src/collective/js/leaflet/upgrades.zcml
src/collective/js/leaflet/browser/__init__.py
src/collective/js/leaflet/browser/configure.zcml
src/collective/js/leaflet/browser/map.pt
src/collective/js/leaflet/browser/view.py
src/collective/js/leaflet/browser/resources/L.GeoSearch/readme.md
src/collective/js/leaflet/browser/resources/L.GeoSearch/example/bing.html
src/collective/js/leaflet/browser/resources/L.GeoSearch/example/esri.html
src/collective/js/leaflet/browser/resources/L.GeoSearch/example/google.html
src/collective/js/leaflet/browser/resources/L.GeoSearch/example/nokia.html
src/collective/js/leaflet/browser/resources/L.GeoSearch/example/openstreetmap.html
src/collective/js/leaflet/browser/resources/L.GeoSearch/src/css/l.geosearch.css
src/collective/js/leaflet/browser/resources/L.GeoSearch/src/js/l.control.geosearch.js
src/collective/js/leaflet/browser/resources/L.GeoSearch/src/js/l.geosearch.provider.bing.js
src/collective/js/leaflet/browser/resources/L.GeoSearch/src/js/l.geosearch.provider.esri.js
src/collective/js/leaflet/browser/resources/L.GeoSearch/src/js/l.geosearch.provider.google.js
src/collective/js/leaflet/browser/resources/L.GeoSearch/src/js/l.geosearch.provider.nokia.js
src/collective/js/leaflet/browser/resources/L.GeoSearch/src/js/l.geosearch.provider.openstreetmap.js
src/collective/js/leaflet/browser/resources/Leaflet/.gitignore
src/collective/js/leaflet/browser/resources/Leaflet/CHANGELOG.md
src/collective/js/leaflet/browser/resources/Leaflet/CONTRIBUTING.md
