Metadata-Version: 2.1
Name: collective.js.leaflet
Version: 1.0.0
Summary: Leaflet maps integration for Plone
Home-page: http://pypi.python.org/pypi/collective.js.leaflet
Author: kiorky
Author-email: kiorky@cryptelium.net
License: GPL
Keywords: plone leaflet gis geo
Platform: UNKNOWN
Classifier: Framework :: Plone
Classifier: Framework :: Plone :: 5.0
Classifier: Programming Language :: Python
Classifier: Topic :: Software Development
Provides-Extra: test
